jsonl2x/__init__.py
jsonl2x/main.py
jsonl2x-0.1.3.dist-info/METADATA
jsonl2x-0.1.3.dist-info/WHEEL
jsonl2x-0.1.3.dist-info/entry_points.txt
jsonl2x-0.1.3.dist-info/top_level.txt
jsonl2x-0.1.3.dist-info/RECORD
